prompta/__init__.py
prompta/__main__.py
prompta/client.py
prompta/config.py
prompta/exceptions.py
prompta/main.py
prompta/models.py
prompta/tracking.py
prompta/commands/__init__.py
prompta/commands/info.py
prompta/commands/projects.py
prompta/commands/prompts.py
prompta/project/__init__.py
prompta/utils/__init__.py
prompta/utils/auth.py
prompta-0.4.1.dist-info/licenses/LICENSE
prompta-0.4.1.dist-info/METADATA
prompta-0.4.1.dist-info/WHEEL
prompta-0.4.1.dist-info/entry_points.txt
prompta-0.4.1.dist-info/top_level.txt
prompta-0.4.1.dist-info/RECORD
