Metadata-Version: 2.4
Name: prompta
Version: 0.4.1
Summary: A powerful CLI tool for managing and versioning prompts across projects
Author-email: Ekky Armandi <me@ekky.dev>
License: MIT License
Project-URL: Homepage, https://github.com/ekkyarmandi/prompta
Project-URL: Bug Tracker, https://github.com/ekkyarmandi/prompta/issues
Project-URL: Source Code, https://github.com/ekkyarmandi/prompta
Keywords: prompts,rules,ai,llm,context,version-control,prompt-management
Classifier: Development Status :: 2 - Pre-Alpha
Classifier: Environment :: Console
Classifier: Intended Audience :: Developers
Classifier: License :: OSI Approved :: MIT License
Classifier: Operating System :: OS Independent
Classifier: Programming Language :: Python :: 3
Classifier: Programming Language :: Python :: 3.8
Classifier: Programming Language :: Python :: 3.9
Classifier: Programming Language :: Python :: 3.10
Classifier: Programming Language :: Python :: 3.11
Classifier: Programming Language :: Python :: 3.12
Classifier: Topic :: Software Development
Classifier: Topic :: Text Processing
Classifier: Topic :: Utilities
Requires-Python: >=3.8.1
License-File: LICENSE
Requires-Dist: click>=8.0.0
Requires-Dist: httpx>=0.24.0
Requires-Dist: rich>=13.0.0
Requires-Dist: python-dotenv>=1.0.0
Requires-Dist: tqdm>=4.64.0
Requires-Dist: pydantic>=2.0.0
Provides-Extra: dev
Requires-Dist: pytest>=7.0.0; extra == "dev"
Requires-Dist: pytest-cov>=4.0.0; extra == "dev"
Requires-Dist: pytest-mock>=3.10.0; extra == "dev"
Requires-Dist: pytest-click>=1.1.0; extra == "dev"
Requires-Dist: black>=23.0.0; extra == "dev"
Requires-Dist: isort>=5.12.0; extra == "dev"
Requires-Dist: flake8>=6.0.0; extra == "dev"
Requires-Dist: mypy>=1.0.0; extra == "dev"
Requires-Dist: responses>=0.23.0; extra == "dev"
Dynamic: license-file
